[
  {
    "SavedGroupId": 23,
    "GroupName": "AllRegion",
    "GroupType": "Region",
    "Settings": "[\"IE\", \"IE-CE\", \"IE-CN\", \"IE-CO\", \"IE-CW\", \"IE-D\", \"IE-DL\", \"IE-G\", \"IE-KE\", \"IE-KK\", \"IE-KY\", \"IE-LD\", \"IE-LH\", \"IE-LK\", \"IE-LM\", \"IE-LS\", \"IE-MH\", \"IE-MN\", \"IE-MO\", \"IE-OY\", \"IE-RN\", \"IE-SO\", \"IE-TA\", \"IE-WD\", \"IE-WH\", \"IE-WW\", \"IE-WX\", \"National\"]",
    "CreatedOn": "2022-09-26 22:06",
    "DisplayCreatedOn": "2022-09-26 22:06",
    "UserName": "olex"
  },
  {
    "SavedGroupId": 22,
    "GroupName": "AllScenario",
    "GroupType": "Scenario",
    "Settings": "[{\"Name\": \"BASE\", \"Checked\": true, \"RowOrder\": 0, \"ShortName\": \"B\"}, {\"Name\": \"IND_CCS\", \"Checked\": true, \"RowOrder\": 1, \"ShortName\": \"SR\"}, {\"Name\": \"PWR_DH\", \"Checked\": true, \"RowOrder\": 2, \"ShortName\": \"SR\"}, {\"Name\": \"PWR_ElectricityStorage\", \"Checked\": false, \"RowOrder\": 3, \"ShortName\": \"SR\"}, {\"Name\": \"PWR_NewTechs\", \"Checked\": true, \"RowOrder\": 4, \"ShortName\": \"SR\"}, {\"Name\": \"RSD-Retrofit\", \"Checked\": true, \"RowOrder\": 5, \"ShortName\": \"SR\"}, {\"Name\": \"RSD_NewTechs\", \"Checked\": true, \"RowOrder\": 6, \"ShortName\": \"SR\"}, {\"Name\": \"SRV_DC_ExcessHeat\", \"Checked\": true, \"RowOrder\": 7, \"ShortName\": \"SR\"}, {\"Name\": \"SRV_NewTechs\", \"Checked\": true, \"RowOrder\": 8, \"ShortName\": \"SR\"}, {\"Name\": \"SUP_BioRefineries\", \"Checked\": true, \"RowOrder\": 9, \"ShortName\": \"SR\"}, {\"Name\": \"SUP_Hydrogen\", \"Checked\": true, \"RowOrder\": 10, \"ShortName\": \"SR\"}, {\"Name\": \"SYS_OtherNewTechs\", \"Checked\": true, \"RowOrder\": 11, \"ShortName\": \"SR\"}, {\"Name\": \"TRA_NewVehicles\", \"Checked\": true, \"RowOrder\": 12, \"ShortName\": \"SR\"}, {\"Name\": \"SysSettings\", \"Checked\": true, \"RowOrder\": 13, \"ShortName\": \"SS\"}, {\"Name\": \"A_SYS_SAD_40TS\", \"Checked\": true, \"RowOrder\": 14, \"ShortName\": \"RS\"}, {\"Name\": \"B_IND_Emi_Proc\", \"Checked\": true, \"RowOrder\": 15, \"ShortName\": \"RS\"}, {\"Name\": \"B_IND_Emissions\", \"Checked\": true, \"RowOrder\": 16, \"ShortName\": \"RS\"}, {\"Name\": \"B_IND_Mitigations\", \"Checked\": true, \"RowOrder\": 17, \"ShortName\": \"RS\"}, {\"Name\": \"B_PWR_CCS\", \"Checked\": true, \"RowOrder\": 18, \"ShortName\": \"RS\"}, {\"Name\": \"B_PWR_RNW_Potentials\", \"Checked\": true, \"RowOrder\": 19, \"ShortName\": \"RS\"}, {\"Name\": \"B_PWR_SNSP_Limit\", \"Checked\": true, \"RowOrder\": 20, \"ShortName\": \"RS\"}, {\"Name\": \"B_RSD_Retrofit-Ctrl\", \"Checked\": true, \"RowOrder\": 21, \"ShortName\": \"RS\"}, {\"Name\": \"B_RSD_UC\", \"Checked\": true, \"RowOrder\": 22, \"ShortName\": \"RS\"}, {\"Name\": \"B_RSD_UnitBoilers\", \"Checked\": true, \"RowOrder\": 23, \"ShortName\": \"RS\"}, {\"Name\": \"B_SRV_DC_EH\", \"Checked\": true, \"RowOrder\": 24, \"ShortName\": \"RS\"}, {\"Name\": \"B_SRV_UC\", \"Checked\": true, \"RowOrder\": 25, \"ShortName\": \"RS\"}, {\"Name\": \"B_SUP_DomBioPot_Baseline\", \"Checked\": true, \"RowOrder\": 26, \"ShortName\": \"RS\"}, {\"Name\": \"B_SYS_Additional_Assumptions\", \"Checked\": true, \"RowOrder\": 27, \"ShortName\": \"RS\"}, {\"Name\": \"B_SYS_Bio_DelivCost\", \"Checked\": true, \"RowOrder\": 28, \"ShortName\": \"RS\"}, {\"Name\": \"B_SYS_Demands\", \"Checked\": true, \"RowOrder\": 29, \"ShortName\": \"RS\"}, {\"Name\": \"B_SYS_Historic_Bounds\", \"Checked\": true, \"RowOrder\": 30, \"ShortName\": \"RS\"}, {\"Name\": \"B_SYS_MaxGrowthRates\", \"Checked\": true, \"RowOrder\": 31, \"ShortName\": \"RS\"}, {\"Name\": \"B_TRA_Emissions\", \"Checked\": true, \"RowOrder\": 32, \"ShortName\": \"RS\"}, {\"Name\": \"B_TRA_EV_Parity\", \"Checked\": true, \"RowOrder\": 33, \"ShortName\": \"RS\"}, {\"Name\": \"B_TRA_F_ModalShares\", \"Checked\": true, \"RowOrder\": 34, \"ShortName\": \"RS\"}, {\"Name\": \"B_TRA_NewCars_Retirement\", \"Checked\": true, \"RowOrder\": 35, \"ShortName\": \"RS\"}, {\"Name\": \"B_TRA_P_ModalShares\", \"Checked\": true, \"RowOrder\": 36, \"ShortName\": \"RS\"}, {\"Name\": \"B_TRA_Stock_Retirement\", \"Checked\": true, \"RowOrder\": 37, \"ShortName\": \"RS\"}, {\"Name\": \"SYS_CarbonBudget\", \"Checked\": true, \"RowOrder\": 45, \"ShortName\": \"RS\"}, {\"Name\": \"SYS_CarbonBudget_Sector\", \"Checked\": true, \"RowOrder\": 47, \"ShortName\": \"RS\"}, {\"Name\": \"SYS_Demands_LED\", \"Checked\": true, \"RowOrder\": 48, \"ShortName\": \"RS\"}, {\"Name\": \"SYS_Demands_LED-Halfway\", \"Checked\": true, \"RowOrder\": 49, \"ShortName\": \"RS\"}, {\"Name\": \"TRA_P_ModalShares_LED\", \"Checked\": true, \"RowOrder\": 52, \"ShortName\": \"RS\"}, {\"Name\": \"TRA_P_ModalShares_LED-halfway\", \"Checked\": true, \"RowOrder\": 53, \"ShortName\": \"RS\"}]",
    "CreatedOn": "2022-10-04 21:09",
    "DisplayCreatedOn": "2022-10-04 21:09",
    "UserName": "olex"
  },
  {
    "SavedGroupId": 32,
    "GroupName": "Counties",
    "GroupType": "Region",
    "Settings": "[\"IE-CE\", \"IE-CN\", \"IE-CO\", \"IE-CW\", \"IE-D\", \"IE-DL\", \"IE-G\", \"IE-KE\", \"IE-KK\", \"IE-KY\", \"IE-LD\", \"IE-LH\", \"IE-LK\", \"IE-LM\", \"IE-LS\", \"IE-MH\", \"IE-MN\", \"IE-MO\", \"IE-OY\", \"IE-RN\", \"IE-SO\", \"IE-TA\", \"IE-WD\", \"IE-WH\", \"IE-WW\", \"IE-WX\", \"National\"]",
    "CreatedOn": "2022-02-22 20:47",
    "DisplayCreatedOn": "2022-02-22 20:47",
    "UserName": "olex"
  },
  {
    "SavedGroupId": 24,
    "GroupName": "DefaultProperties",
    "GroupType": "Properties",
    "Settings": "{\"OptCa\": null, \"OptCr\": null, \"Damage\": 2, \"LimCol\": 0, \"LimRow\": 0, \"Oblong\": true, \"ResLim\": 50000, \"Retire\": false, \"IterLim\": 999999, \"SolPrint\": false, \"Uncertainty\": 0, \"RunInStepsOf\": 0, \"ClimateModule\": false, \"LinearVarCost\": true, \"LevelizedCosts\": 3, \"GamsOptionBratio\": \"\", \"DiscreteInvestment\": false, \"DoExtendedQaChecks\": false, \"GeneralEquilibrium\": 3, \"MidYearDiscounting\": true, \"ObjFunctionVariant\": 0, \"ShiftDiscountingBy\": 0, \"Co2CalibrationAtBoh\": false, \"UseSlackVariablesInUc\": false, \"DiscreteUnitCommitment\": false, \"EndoGenousTechLearning\": false, \"WriteBPriceforElastDem\": false, \"SaveSolutionInformation\": false, \"TsForFlowReportingTypes\": 0, \"UseLastRunAsStartingPoint\": false, \"ActivateSensitivityAnalysis\": false}",
    "CreatedOn": "2022-09-26 22:06",
    "DisplayCreatedOn": "2022-09-26 22:06",
    "UserName": "olex"
  },
  {
    "SavedGroupId": 26,
    "GroupName": "MitigationSectoralCBs",
    "GroupType": "Scenario",
    "Settings": "[{\"Name\": \"BASE\", \"Checked\": true, \"RowOrder\": 0, \"ShortName\": \"B\"}, {\"Name\": \"IND_CCS\", \"Checked\": true, \"RowOrder\": 1, \"ShortName\": \"SR\"}, {\"Name\": \"PWR_DH\", \"Checked\": true, \"RowOrder\": 2, \"ShortName\": \"SR\"}, {\"Name\": \"PWR_NewTechs\", \"Checked\": true, \"RowOrder\": 3, \"ShortName\": \"SR\"}, {\"Name\": \"RSD-Retrofit\", \"Checked\": true, \"RowOrder\": 4, \"ShortName\": \"SR\"}, {\"Name\": \"RSD_NewTechs\", \"Checked\": true, \"RowOrder\": 5, \"ShortName\": \"SR\"}, {\"Name\": \"SRV_DC_ExcessHeat\", \"Checked\": true, \"RowOrder\": 6, \"ShortName\": \"SR\"}, {\"Name\": \"SRV_NewTechs\", \"Checked\": true, \"RowOrder\": 7, \"ShortName\": \"SR\"}, {\"Name\": \"SUP_BioRefineries\", \"Checked\": true, \"RowOrder\": 8, \"ShortName\": \"SR\"}, {\"Name\": \"PWR_ElectricityStorage\", \"Checked\": false, \"RowOrder\": 9, \"ShortName\": \"SR\"}, {\"Name\": \"SUP_Hydrogen\", \"Checked\": true, \"RowOrder\": 10, \"ShortName\": \"SR\"}, {\"Name\": \"SYS_OtherNewTechs\", \"Checked\": true, \"RowOrder\": 11, \"ShortName\": \"SR\"}, {\"Name\": \"TRA_NewVehicles\", \"Checked\": true, \"RowOrder\": 12, \"ShortName\": \"SR\"}, {\"Name\": \"SysSettings\", \"Checked\": true, \"RowOrder\": 13, \"ShortName\": \"SS\"}, {\"Name\": \"B_SYS_Additional_Assumptions\", \"Checked\": true, \"RowOrder\": 14, \"ShortName\": \"RS\"}, {\"Name\": \"B_SYS_Demands\", \"Checked\": true, \"RowOrder\": 15, \"ShortName\": \"RS\"}, {\"Name\": \"B_SUP_DomBioPot_Baseline\", \"Checked\": true, \"RowOrder\": 16, \"ShortName\": \"RS\"}, {\"Name\": \"B_IND_Emi_Proc\", \"Checked\": true, \"RowOrder\": 17, \"ShortName\": \"RS\"}, {\"Name\": \"B_IND_Mitigations\", \"Checked\": true, \"RowOrder\": 18, \"ShortName\": \"RS\"}, {\"Name\": \"B_PWR_CCS\", \"Checked\": true, \"RowOrder\": 19, \"ShortName\": \"RS\"}, {\"Name\": \"B_SRV_DC_EH\", \"Checked\": true, \"RowOrder\": 20, \"ShortName\": \"RS\"}, {\"Name\": \"A_SYS_SAD_40TS\", \"Checked\": true, \"RowOrder\": 21, \"ShortName\": \"RS\"}, {\"Name\": \"B_PWR_RNW_Potentials\", \"Checked\": true, \"RowOrder\": 22, \"ShortName\": \"RS\"}, {\"Name\": \"B_SYS_Historic_Bounds\", \"Checked\": true, \"RowOrder\": 23, \"ShortName\": \"RS\"}, {\"Name\": \"B_IND_Emissions\", \"Checked\": true, \"RowOrder\": 24, \"ShortName\": \"RS\"}, {\"Name\": \"B_RSD_Retrofit-Ctrl\", \"Checked\": true, \"RowOrder\": 25, \"ShortName\": \"RS\"}, {\"Name\": \"B_RSD_UC\", \"Checked\": true, \"RowOrder\": 26, \"ShortName\": \"RS\"}, {\"Name\": \"B_SRV_UC\", \"Checked\": true, \"RowOrder\": 27, \"ShortName\": \"RS\"}, {\"Name\": \"B_PWR_SNSP_Limit\", \"Checked\": true, \"RowOrder\": 28, \"ShortName\": \"RS\"}, {\"Name\": \"B_SYS_Bio_DelivCost\", \"Checked\": true, \"RowOrder\": 29, \"ShortName\": \"RS\"}, {\"Name\": \"SYS_Demands_LED\", \"Checked\": false, \"RowOrder\": 31, \"ShortName\": \"RS\"}, {\"Name\": \"SYS_Demands_LED-Halfway\", \"Checked\": false, \"RowOrder\": 32, \"ShortName\": \"RS\"}, {\"Name\": \"B_SYS_MaxGrowthRates\", \"Checked\": true, \"RowOrder\": 33, \"ShortName\": \"RS\"}, {\"Name\": \"B_RSD_UnitBoilers\", \"Checked\": true, \"RowOrder\": 35, \"ShortName\": \"RS\"}, {\"Name\": \"B_TRA_P_ModalShares\", \"Checked\": true, \"RowOrder\": 37, \"ShortName\": \"RS\"}, {\"Name\": \"TRA_P_ModalShares_LED\", \"Checked\": false, \"RowOrder\": 38, \"ShortName\": \"RS\"}, {\"Name\": \"TRA_P_ModalShares_LED-halfway\", \"Checked\": false, \"RowOrder\": 40, \"ShortName\": \"RS\"}, {\"Name\": \"SYS_CarbonBudget\", \"Checked\": true, \"RowOrder\": 41, \"ShortName\": \"RS\"}, {\"Name\": \"SYS_CarbonBudget_Sector\", \"Checked\": true, \"RowOrder\": 43, \"ShortName\": \"RS\"}, {\"Name\": \"B_TRA_NewCars_Retirement\", \"Checked\": true, \"RowOrder\": 44, \"ShortName\": \"RS\"}, {\"Name\": \"B_TRA_Stock_Retirement\", \"Checked\": true, \"RowOrder\": 45, \"ShortName\": \"RS\"}, {\"Name\": \"B_TRA_Emissions\", \"Checked\": true, \"RowOrder\": 46, \"ShortName\": \"RS\"}, {\"Name\": \"B_TRA_EV_Parity\", \"Checked\": true, \"RowOrder\": 47, \"ShortName\": \"RS\"}, {\"Name\": \"B_TRA_F_ModalShares\", \"Checked\": true, \"RowOrder\": 48, \"ShortName\": \"RS\"}]",
    "CreatedOn": "2022-10-04 21:08",
    "DisplayCreatedOn": "2022-10-04 21:08",
    "UserName": "olex"
  },
  {
    "SavedGroupId": 60,
    "GroupName": "MitigationSectoralCBs-LED",
    "GroupType": "Scenario",
    "Settings": "[{\"Name\": \"BASE\", \"Checked\": true, \"RowOrder\": 0, \"ShortName\": \"B\"}, {\"Name\": \"IND_CCS\", \"Checked\": true, \"RowOrder\": 1, \"ShortName\": \"SR\"}, {\"Name\": \"PWR_DH\", \"Checked\": true, \"RowOrder\": 2, \"ShortName\": \"SR\"}, {\"Name\": \"PWR_NewTechs\", \"Checked\": true, \"RowOrder\": 3, \"ShortName\": \"SR\"}, {\"Name\": \"RSD-Retrofit\", \"Checked\": true, \"RowOrder\": 4, \"ShortName\": \"SR\"}, {\"Name\": \"RSD_NewTechs\", \"Checked\": true, \"RowOrder\": 5, \"ShortName\": \"SR\"}, {\"Name\": \"SRV_DC_ExcessHeat\", \"Checked\": true, \"RowOrder\": 6, \"ShortName\": \"SR\"}, {\"Name\": \"SRV_NewTechs\", \"Checked\": true, \"RowOrder\": 7, \"ShortName\": \"SR\"}, {\"Name\": \"SUP_BioRefineries\", \"Checked\": true, \"RowOrder\": 8, \"ShortName\": \"SR\"}, {\"Name\": \"PWR_ElectricityStorage\", \"Checked\": false, \"RowOrder\": 9, \"ShortName\": \"SR\"}, {\"Name\": \"SUP_Hydrogen\", \"Checked\": true, \"RowOrder\": 10, \"ShortName\": \"SR\"}, {\"Name\": \"SYS_OtherNewTechs\", \"Checked\": true, \"RowOrder\": 11, \"ShortName\": \"SR\"}, {\"Name\": \"TRA_NewVehicles\", \"Checked\": true, \"RowOrder\": 12, \"ShortName\": \"SR\"}, {\"Name\": \"SysSettings\", \"Checked\": true, \"RowOrder\": 13, \"ShortName\": \"SS\"}, {\"Name\": \"B_SYS_Additional_Assumptions\", \"Checked\": true, \"RowOrder\": 14, \"ShortName\": \"RS\"}, {\"Name\": \"B_SYS_Demands\", \"Checked\": false, \"RowOrder\": 15, \"ShortName\": \"RS\"}, {\"Name\": \"B_SUP_DomBioPot_Baseline\", \"Checked\": true, \"RowOrder\": 16, \"ShortName\": \"RS\"}, {\"Name\": \"B_IND_Emi_Proc\", \"Checked\": true, \"RowOrder\": 17, \"ShortName\": \"RS\"}, {\"Name\": \"B_IND_Mitigations\", \"Checked\": true, \"RowOrder\": 18, \"ShortName\": \"RS\"}, {\"Name\": \"B_PWR_CCS\", \"Checked\": true, \"RowOrder\": 19, \"ShortName\": \"RS\"}, {\"Name\": \"B_SRV_DC_EH\", \"Checked\": true, \"RowOrder\": 20, \"ShortName\": \"RS\"}, {\"Name\": \"A_SYS_SAD_40TS\", \"Checked\": true, \"RowOrder\": 21, \"ShortName\": \"RS\"}, {\"Name\": \"B_PWR_RNW_Potentials\", \"Checked\": true, \"RowOrder\": 22, \"ShortName\": \"RS\"}, {\"Name\": \"B_SYS_Historic_Bounds\", \"Checked\": true, \"RowOrder\": 23, \"ShortName\": \"RS\"}, {\"Name\": \"B_IND_Emissions\", \"Checked\": true, \"RowOrder\": 24, \"ShortName\": \"RS\"}, {\"Name\": \"B_RSD_Retrofit-Ctrl\", \"Checked\": true, \"RowOrder\": 25, \"ShortName\": \"RS\"}, {\"Name\": \"B_RSD_UC\", \"Checked\": true, \"RowOrder\": 26, \"ShortName\": \"RS\"}, {\"Name\": \"B_SRV_UC\", \"Checked\": true, \"RowOrder\": 27, \"ShortName\": \"RS\"}, {\"Name\": \"B_PWR_SNSP_Limit\", \"Checked\": true, \"RowOrder\": 28, \"ShortName\": \"RS\"}, {\"Name\": \"B_SYS_Bio_DelivCost\", \"Checked\": true, \"RowOrder\": 29, \"ShortName\": \"RS\"}, {\"Name\": \"SYS_Demands_LED\", \"Checked\": true, \"RowOrder\": 31, \"ShortName\": \"RS\"}, {\"Name\": \"SYS_Demands_LED-Halfway\", \"Checked\": false, \"RowOrder\": 32, \"ShortName\": \"RS\"}, {\"Name\": \"B_SYS_MaxGrowthRates\", \"Checked\": true, \"RowOrder\": 33, \"ShortName\": \"RS\"}, {\"Name\": \"B_RSD_UnitBoilers\", \"Checked\": true, \"RowOrder\": 35, \"ShortName\": \"RS\"}, {\"Name\": \"B_TRA_P_ModalShares\", \"Checked\": false, \"RowOrder\": 37, \"ShortName\": \"RS\"}, {\"Name\": \"TRA_P_ModalShares_LED\", \"Checked\": true, \"RowOrder\": 38, \"ShortName\": \"RS\"}, {\"Name\": \"TRA_P_ModalShares_LED-halfway\", \"Checked\": false, \"RowOrder\": 40, \"ShortName\": \"RS\"}, {\"Name\": \"SYS_CarbonBudget\", \"Checked\": true, \"RowOrder\": 41, \"ShortName\": \"RS\"}, {\"Name\": \"SYS_CarbonBudget_Sector\", \"Checked\": true, \"RowOrder\": 43, \"ShortName\": \"RS\"}, {\"Name\": \"B_TRA_NewCars_Retirement\", \"Checked\": true, \"RowOrder\": 44, \"ShortName\": \"RS\"}, {\"Name\": \"B_TRA_Stock_Retirement\", \"Checked\": true, \"RowOrder\": 45, \"ShortName\": \"RS\"}, {\"Name\": \"B_TRA_Emissions\", \"Checked\": true, \"RowOrder\": 46, \"ShortName\": \"RS\"}, {\"Name\": \"B_TRA_EV_Parity\", \"Checked\": true, \"RowOrder\": 47, \"ShortName\": \"RS\"}, {\"Name\": \"B_TRA_F_ModalShares\", \"Checked\": true, \"RowOrder\": 48, \"ShortName\": \"RS\"}]",
    "CreatedOn": "2022-10-04 21:08",
    "DisplayCreatedOn": "2022-10-04 21:08",
    "UserName": "olex"
  },
  {
    "SavedGroupId": 28,
    "GroupName": "MitigationSectoralCBs-LED_Halfway",
    "GroupType": "Scenario",
    "Settings": "[{\"Name\": \"BASE\", \"Checked\": true, \"RowOrder\": 0, \"ShortName\": \"B\"}, {\"Name\": \"IND_CCS\", \"Checked\": true, \"RowOrder\": 1, \"ShortName\": \"SR\"}, {\"Name\": \"PWR_DH\", \"Checked\": true, \"RowOrder\": 2, \"ShortName\": \"SR\"}, {\"Name\": \"PWR_NewTechs\", \"Checked\": true, \"RowOrder\": 3, \"ShortName\": \"SR\"}, {\"Name\": \"RSD-Retrofit\", \"Checked\": true, \"RowOrder\": 4, \"ShortName\": \"SR\"}, {\"Name\": \"RSD_NewTechs\", \"Checked\": true, \"RowOrder\": 5, \"ShortName\": \"SR\"}, {\"Name\": \"SRV_DC_ExcessHeat\", \"Checked\": true, \"RowOrder\": 6, \"ShortName\": \"SR\"}, {\"Name\": \"SRV_NewTechs\", \"Checked\": true, \"RowOrder\": 7, \"ShortName\": \"SR\"}, {\"Name\": \"SUP_BioRefineries\", \"Checked\": true, \"RowOrder\": 8, \"ShortName\": \"SR\"}, {\"Name\": \"PWR_ElectricityStorage\", \"Checked\": false, \"RowOrder\": 9, \"ShortName\": \"SR\"}, {\"Name\": \"SUP_Hydrogen\", \"Checked\": true, \"RowOrder\": 10, \"ShortName\": \"SR\"}, {\"Name\": \"SYS_OtherNewTechs\", \"Checked\": true, \"RowOrder\": 11, \"ShortName\": \"SR\"}, {\"Name\": \"TRA_NewVehicles\", \"Checked\": true, \"RowOrder\": 12, \"ShortName\": \"SR\"}, {\"Name\": \"SysSettings\", \"Checked\": true, \"RowOrder\": 13, \"ShortName\": \"SS\"}, {\"Name\": \"B_SYS_Additional_Assumptions\", \"Checked\": true, \"RowOrder\": 14, \"ShortName\": \"RS\"}, {\"Name\": \"B_SYS_Demands\", \"Checked\": false, \"RowOrder\": 15, \"ShortName\": \"RS\"}, {\"Name\": \"B_SUP_DomBioPot_Baseline\", \"Checked\": true, \"RowOrder\": 16, \"ShortName\": \"RS\"}, {\"Name\": \"B_IND_Emi_Proc\", \"Checked\": true, \"RowOrder\": 17, \"ShortName\": \"RS\"}, {\"Name\": \"B_IND_Mitigations\", \"Checked\": true, \"RowOrder\": 18, \"ShortName\": \"RS\"}, {\"Name\": \"B_PWR_CCS\", \"Checked\": true, \"RowOrder\": 19, \"ShortName\": \"RS\"}, {\"Name\": \"B_SRV_DC_EH\", \"Checked\": true, \"RowOrder\": 20, \"ShortName\": \"RS\"}, {\"Name\": \"A_SYS_SAD_40TS\", \"Checked\": true, \"RowOrder\": 21, \"ShortName\": \"RS\"}, {\"Name\": \"B_PWR_RNW_Potentials\", \"Checked\": true, \"RowOrder\": 22, \"ShortName\": \"RS\"}, {\"Name\": \"B_SYS_Historic_Bounds\", \"Checked\": true, \"RowOrder\": 23, \"ShortName\": \"RS\"}, {\"Name\": \"B_IND_Emissions\", \"Checked\": true, \"RowOrder\": 24, \"ShortName\": \"RS\"}, {\"Name\": \"B_RSD_Retrofit-Ctrl\", \"Checked\": true, \"RowOrder\": 25, \"ShortName\": \"RS\"}, {\"Name\": \"B_RSD_UC\", \"Checked\": true, \"RowOrder\": 26, \"ShortName\": \"RS\"}, {\"Name\": \"B_SRV_UC\", \"Checked\": true, \"RowOrder\": 27, \"ShortName\": \"RS\"}, {\"Name\": \"B_PWR_SNSP_Limit\", \"Checked\": true, \"RowOrder\": 28, \"ShortName\": \"RS\"}, {\"Name\": \"B_SYS_Bio_DelivCost\", \"Checked\": true, \"RowOrder\": 29, \"ShortName\": \"RS\"}, {\"Name\": \"SYS_Demands_LED\", \"Checked\": false, \"RowOrder\": 31, \"ShortName\": \"RS\"}, {\"Name\": \"SYS_Demands_LED-Halfway\", \"Checked\": true, \"RowOrder\": 32, \"ShortName\": \"RS\"}, {\"Name\": \"B_SYS_MaxGrowthRates\", \"Checked\": true, \"RowOrder\": 33, \"ShortName\": \"RS\"}, {\"Name\": \"B_RSD_UnitBoilers\", \"Checked\": true, \"RowOrder\": 35, \"ShortName\": \"RS\"}, {\"Name\": \"B_TRA_P_ModalShares\", \"Checked\": false, \"RowOrder\": 37, \"ShortName\": \"RS\"}, {\"Name\": \"TRA_P_ModalShares_LED\", \"Checked\": false, \"RowOrder\": 38, \"ShortName\": \"RS\"}, {\"Name\": \"TRA_P_ModalShares_LED-halfway\", \"Checked\": true, \"RowOrder\": 40, \"ShortName\": \"RS\"}, {\"Name\": \"SYS_CarbonBudget\", \"Checked\": true, \"RowOrder\": 41, \"ShortName\": \"RS\"}, {\"Name\": \"SYS_CarbonBudget_Sector\", \"Checked\": true, \"RowOrder\": 43, \"ShortName\": \"RS\"}, {\"Name\": \"B_TRA_NewCars_Retirement\", \"Checked\": true, \"RowOrder\": 44, \"ShortName\": \"RS\"}, {\"Name\": \"B_TRA_Stock_Retirement\", \"Checked\": true, \"RowOrder\": 45, \"ShortName\": \"RS\"}, {\"Name\": \"B_TRA_Emissions\", \"Checked\": true, \"RowOrder\": 46, \"ShortName\": \"RS\"}, {\"Name\": \"B_TRA_EV_Parity\", \"Checked\": true, \"RowOrder\": 47, \"ShortName\": \"RS\"}, {\"Name\": \"B_TRA_F_ModalShares\", \"Checked\": true, \"RowOrder\": 48, \"ShortName\": \"RS\"}]",
    "CreatedOn": "2022-10-04 21:08",
    "DisplayCreatedOn": "2022-10-04 21:08",
    "UserName": "olex"
  },
  {
    "SavedGroupId": 30,
    "GroupName": "NoMitigation",
    "GroupType": "Scenario",
    "Settings": "[{\"Name\": \"BASE\", \"Checked\": true, \"RowOrder\": 0, \"ShortName\": \"B\"}, {\"Name\": \"IND_CCS\", \"Checked\": false, \"RowOrder\": 1, \"ShortName\": \"SR\"}, {\"Name\": \"PWR_DH\", \"Checked\": true, \"RowOrder\": 2, \"ShortName\": \"SR\"}, {\"Name\": \"PWR_NewTechs\", \"Checked\": true, \"RowOrder\": 3, \"ShortName\": \"SR\"}, {\"Name\": \"RSD-Retrofit\", \"Checked\": true, \"RowOrder\": 4, \"ShortName\": \"SR\"}, {\"Name\": \"RSD_NewTechs\", \"Checked\": true, \"RowOrder\": 5, \"ShortName\": \"SR\"}, {\"Name\": \"SRV_DC_ExcessHeat\", \"Checked\": true, \"RowOrder\": 6, \"ShortName\": \"SR\"}, {\"Name\": \"SRV_NewTechs\", \"Checked\": true, \"RowOrder\": 7, \"ShortName\": \"SR\"}, {\"Name\": \"SUP_BioRefineries\", \"Checked\": true, \"RowOrder\": 8, \"ShortName\": \"SR\"}, {\"Name\": \"PWR_ElectricityStorage\", \"Checked\": false, \"RowOrder\": 9, \"ShortName\": \"SR\"}, {\"Name\": \"SUP_Hydrogen\", \"Checked\": true, \"RowOrder\": 10, \"ShortName\": \"SR\"}, {\"Name\": \"SYS_OtherNewTechs\", \"Checked\": true, \"RowOrder\": 11, \"ShortName\": \"SR\"}, {\"Name\": \"TRA_NewVehicles\", \"Checked\": true, \"RowOrder\": 12, \"ShortName\": \"SR\"}, {\"Name\": \"SysSettings\", \"Checked\": true, \"RowOrder\": 13, \"ShortName\": \"SS\"}, {\"Name\": \"B_SYS_Additional_Assumptions\", \"Checked\": true, \"RowOrder\": 14, \"ShortName\": \"RS\"}, {\"Name\": \"B_SYS_Demands\", \"Checked\": true, \"RowOrder\": 15, \"ShortName\": \"RS\"}, {\"Name\": \"B_SUP_DomBioPot_Baseline\", \"Checked\": true, \"RowOrder\": 16, \"ShortName\": \"RS\"}, {\"Name\": \"B_IND_Emi_Proc\", \"Checked\": true, \"RowOrder\": 17, \"ShortName\": \"RS\"}, {\"Name\": \"B_IND_Mitigations\", \"Checked\": false, \"RowOrder\": 18, \"ShortName\": \"RS\"}, {\"Name\": \"B_PWR_CCS\", \"Checked\": true, \"RowOrder\": 19, \"ShortName\": \"RS\"}, {\"Name\": \"B_SRV_DC_EH\", \"Checked\": true, \"RowOrder\": 20, \"ShortName\": \"RS\"}, {\"Name\": \"A_SYS_SAD_40TS\", \"Checked\": true, \"RowOrder\": 21, \"ShortName\": \"RS\"}, {\"Name\": \"B_PWR_RNW_Potentials\", \"Checked\": true, \"RowOrder\": 22, \"ShortName\": \"RS\"}, {\"Name\": \"B_IND_Emissions\", \"Checked\": true, \"RowOrder\": 23, \"ShortName\": \"RS\"}, {\"Name\": \"B_RSD_Retrofit-Ctrl\", \"Checked\": true, \"RowOrder\": 24, \"ShortName\": \"RS\"}, {\"Name\": \"B_RSD_UC\", \"Checked\": true, \"RowOrder\": 25, \"ShortName\": \"RS\"}, {\"Name\": \"B_SRV_UC\", \"Checked\": true, \"RowOrder\": 26, \"ShortName\": \"RS\"}, {\"Name\": \"B_PWR_SNSP_Limit\", \"Checked\": true, \"RowOrder\": 27, \"ShortName\": \"RS\"}, {\"Name\": \"B_SYS_Bio_DelivCost\", \"Checked\": true, \"RowOrder\": 28, \"ShortName\": \"RS\"}, {\"Name\": \"B_SYS_Historic_Bounds\", \"Checked\": true, \"RowOrder\": 29, \"ShortName\": \"RS\"}, {\"Name\": \"SYS_Demands_LED\", \"Checked\": false, \"RowOrder\": 31, \"ShortName\": \"RS\"}, {\"Name\": \"B_SYS_MaxGrowthRates\", \"Checked\": true, \"RowOrder\": 32, \"ShortName\": \"RS\"}, {\"Name\": \"B_RSD_UnitBoilers\", \"Checked\": true, \"RowOrder\": 34, \"ShortName\": \"RS\"}, {\"Name\": \"TRA_P_ModalShares_LED\", \"Checked\": false, \"RowOrder\": 36, \"ShortName\": \"RS\"}, {\"Name\": \"B_TRA_P_ModalShares\", \"Checked\": true, \"RowOrder\": 37, \"ShortName\": \"RS\"}, {\"Name\": \"B_TRA_NewCars_Retirement\", \"Checked\": true, \"RowOrder\": 39, \"ShortName\": \"RS\"}, {\"Name\": \"SYS_CarbonBudget\", \"Checked\": false, \"RowOrder\": 41, \"ShortName\": \"RS\"}, {\"Name\": \"SYS_CarbonBudget_Sector\", \"Checked\": false, \"RowOrder\": 45, \"ShortName\": \"RS\"}, {\"Name\": \"B_TRA_Stock_Retirement\", \"Checked\": true, \"RowOrder\": 46, \"ShortName\": \"RS\"}, {\"Name\": \"B_TRA_Emissions\", \"Checked\": true, \"RowOrder\": 48, \"ShortName\": \"RS\"}, {\"Name\": \"B_TRA_EV_Parity\", \"Checked\": true, \"RowOrder\": 50, \"ShortName\": \"RS\"}, {\"Name\": \"B_TRA_F_ModalShares\", \"Checked\": true, \"RowOrder\": 51, \"ShortName\": \"RS\"}, {\"Name\": \"SYS_Demands_LED-Halfway\", \"Checked\": false, \"RowOrder\": 52, \"ShortName\": \"RS\"}, {\"Name\": \"TRA_P_ModalShares_LED-halfway\", \"Checked\": false, \"RowOrder\": 53, \"ShortName\": \"RS\"}]",
    "CreatedOn": "2022-10-04 21:04",
    "DisplayCreatedOn": "2022-10-04 21:04",
    "UserName": "olex"
  },
  {
    "SavedGroupId": 29,
    "GroupName": "SingleRegion",
    "GroupType": "Region",
    "Settings": "[\"IE\"]",
    "CreatedOn": "2022-02-22 20:46",
    "DisplayCreatedOn": "2022-02-22 20:46",
    "UserName": "olex"
  },
  {
    "SavedGroupId": 59,
    "GroupName": "all_SRV_DC_Demand",
    "GroupType": "Parametric",
    "Settings": "[\"SRV_DC_Demand_0001\", \"SRV_DC_Demand_0002\", \"SRV_DC_Demand_0003\"]",
    "CreatedOn": "2022-10-04 19:52",
    "DisplayCreatedOn": "2022-10-04 19:52",
    "UserName": "olex"
  }
]